topsis/__main__.py
topsis_sidaknoor_102203262-1.0.0.dist-info/LICENSE
topsis_sidaknoor_102203262-1.0.0.dist-info/METADATA
topsis_sidaknoor_102203262-1.0.0.dist-info/WHEEL
topsis_sidaknoor_102203262-1.0.0.dist-info/entry_points.txt
topsis_sidaknoor_102203262-1.0.0.dist-info/top_level.txt
topsis_sidaknoor_102203262-1.0.0.dist-info/RECORD
