Metadata-Version: 2.2
Name: topsis-sidaknoor-102203262
Version: 1.0.0
Summary: A TOPSIS implemented function that returns rank of rows
Home-page: https://test.pypi.org/project/topsis-sidaknoor-102203262/
Download-URL: https://github.com/user/reponame/archive/v_01.tar.gz
Author: Sidak Noor Singh
Author-email: ssingh9_be22@thapr.edu
License: MIT
Classifier: Development Status :: 3 - Alpha
Classifier: Intended Audience :: Developers
Classifier: Topic :: Software Development :: Build Tools
Classifier: License :: OSI Approved :: MIT License
Classifier: Programming Language :: Python :: 3
Classifier: Programming Language :: Python :: 3.4
Classifier: Programming Language :: Python :: 3.5
Classifier: Programming Language :: Python :: 3.6
License-File: LICENSE
Requires-Dist: numpy
Requires-Dist: pandas
Dynamic: author
Dynamic: author-email
Dynamic: classifier
Dynamic: description
Dynamic: description-content-type
Dynamic: download-url
Dynamic: home-page
Dynamic: license
Dynamic: requires-dist
Dynamic: summary
